tests/__init__.py
tests/test_corner_cases.py
tests/test_distances.py
tests/test_phonetics.py
tests/test_utils.py
wltr_phonetics/__init__.py
wltr_phonetics/exceptions.py
wltr_phonetics/utils.py
wltr_phonetics/distance_metrics/__init__.py
wltr_phonetics/distance_metrics/hamming.py
wltr_phonetics/distance_metrics/levenshtein.py
wltr_phonetics/phonetics/__init__.py
wltr_phonetics/phonetics/fuzzy_soundex.py
wltr_phonetics/phonetics/lein.py
wltr_phonetics/phonetics/metaphone.py
wltr_phonetics/phonetics/mra.py
wltr_phonetics/phonetics/phonetic_algorithm.py
wltr_phonetics/phonetics/refined_soundex.py
wltr_phonetics/phonetics/soundex.py
wltr_phonetics-1.0.2.dist-info/METADATA
wltr_phonetics-1.0.2.dist-info/WHEEL
wltr_phonetics-1.0.2.dist-info/top_level.txt
wltr_phonetics-1.0.2.dist-info/RECORD
