Metadata-Version: 2.1
Name: wltr-phonetics
Version: 1.0.2
Summary: Wltr Phonetics é uma biblioteca de algoritmos fonéticos
Home-page: https://github.com/walteravelino/wltr-phonetics
Author: Walter Avelino
Author-email: walter.avelin@gmail.com
License: UNKNOWN
Platform: UNKNOWN
Classifier: Programming Language :: Python :: 3
Classifier: License :: OSI Approved :: MIT License
Classifier: Operating System :: OS Independent
